{
  "title": "event.status",
  "type": "object",
  "description": "Indicates if the [event](../event.json) is still happening or not.",
  "x-examples": {
    "Available": {
      "type": "available"
    },
    "Temporarily Unavailable": {
      "type": "temporarilyUnavailable",
      "reason": {
        "nl": "Uitgesteld wegens covid-19",
        "en": "Postponed due to covid-19"
      }
    },
    "Unavailable": {
      "type": "unavailable",
      "reason": {
        "nl": "Permanent gesloten"
      }
    }
  },
  "properties": {
    "type": {
      "minLength": 1,
      "enum": [
        "available",
        "temporarilyUnavailable",
        "unavailable"
      ],
      "example": "available",
      "description": "One of three possible status types.\n\n- `available`: The event is happening as planned\n- `temporarilyUnavailable`: The event will be postponed\n- `unavailable`: The event is permanently cancelled",
      "type": "string"
    },
    "reason": {
      "$ref": "../localizedString.json",
      "description": "The reason of the status on the event, as a localized human-readable text.",
      "title": "",
      "x-examples": {}
    }
  },
  "required": [
    "type"
  ]
}